{"@context":"https://iiif.io/api/presentation/3/context.json","id":"https://mathewjordan.github.io/canopy-heilman/api/facet/subject/platanthera-ciliaris.json","type":"Collection","label":{"none":["Platanthera ciliaris"]},"items":[{"id":"https://digital.lib.utk.edu/assemble/manifest/heilman/1228","type":"Manifest","label":{"en":["Platanthera ciliaris, 1076"]},"thumbnail":[{"id":"https://digital.lib.utk.edu/iiif/2/collections~islandora~object~heilman%3A1228~datastream~JP2/full/681,463/0/default.jpg","width":681,"height":463,"type":"Image","format":"image/jpeg","service":[{"@id":"https://digital.lib.utk.edu/iiif/2/collections~islandora~object~heilman%3A1228~datastream~JP2","@type":"http://iiif.io/api/image/2/context.json","profile":"http://iiif.io/api/image/2/level2.json"}]}],"homepage":[{"id":"https://mathewjordan.github.io/canopy-heilman/works/platanthera-ciliaris-1076","type":"Text","label":{"en":["Platanthera ciliaris, 1076"]}}]}],"partOf":[{"id":"https://mathewjordan.github.io/canopy-heilman/api/facet/subject.json","type":"Collection"}],"summary":{"none":["Subject"]},"homepage":[{"id":"https://mathewjordan.github.io/canopy-heilman/search?subject=platanthera-ciliaris","type":"Text","label":{"none":["Platanthera ciliaris"]}}]}