{"@context":"https://iiif.io/api/presentation/3/context.json","id":"https://mathewjordan.github.io/canopy-heilman/api/facet/date/3302008.json","type":"Collection","label":{"none":["3/30/2008"]},"items":[{"id":"https://digital.lib.utk.edu/assemble/manifest/heilman/1052","type":"Manifest","label":{"en":["Rosa MELdaud, 0908"]},"thumbnail":[{"id":"https://digital.lib.utk.edu/iiif/2/collections~islandora~object~heilman%3A1052~datastream~JP2/full/467,695/0/default.jpg","width":467,"height":695,"type":"Image","format":"image/jpeg","service":[{"@id":"https://digital.lib.utk.edu/iiif/2/collections~islandora~object~heilman%3A1052~datastream~JP2","@type":"http://iiif.io/api/image/2/context.json","profile":"http://iiif.io/api/image/2/level2.json"}]}],"homepage":[{"id":"https://mathewjordan.github.io/canopy-heilman/works/rosa-meldaud-0908","type":"Text","label":{"en":["Rosa MELdaud, 0908"]}}]},{"id":"https://digital.lib.utk.edu/assemble/manifest/heilman/484","type":"Manifest","label":{"en":["Euphorbia, species indeterminate, 0339"]},"thumbnail":[{"id":"https://digital.lib.utk.edu/iiif/2/collections~islandora~object~heilman%3A484~datastream~JP2/full/683,467/0/default.jpg","width":683,"height":467,"type":"Image","format":"image/jpeg","service":[{"@id":"https://digital.lib.utk.edu/iiif/2/collections~islandora~object~heilman%3A484~datastream~JP2","@type":"http://iiif.io/api/image/2/context.json","profile":"http://iiif.io/api/image/2/level2.json"}]}],"homepage":[{"id":"https://mathewjordan.github.io/canopy-heilman/works/euphorbia-species-indeterminate-0339","type":"Text","label":{"en":["Euphorbia, species indeterminate, 0339"]}}]},{"id":"https://digital.lib.utk.edu/assemble/manifest/heilman/485","type":"Manifest","label":{"en":["Euphorbia xsp.martinii, 0340"]},"thumbnail":[{"id":"https://digital.lib.utk.edu/iiif/2/collections~islandora~object~heilman%3A485~datastream~TN/full/max/0/default.jpg","width":200,"height":137,"service":[{"@id":"https://digital.lib.utk.edu/iiif/2/collections~islandora~object~heilman%3A485~datastream~TN","@type":"http://iiif.io/api/image/2/context.json","@profile":"http://iiif.io/api/image/2/level2.json"}],"type":"Image","format":"image/jpeg"}],"homepage":[{"id":"https://mathewjordan.github.io/canopy-heilman/works/euphorbia-xspmartinii-0340","type":"Text","label":{"en":["Euphorbia xsp.martinii, 0340"]}}]}],"partOf":[{"id":"https://mathewjordan.github.io/canopy-heilman/api/facet/date.json","type":"Collection"}],"summary":{"none":["Date"]},"homepage":[{"id":"https://mathewjordan.github.io/canopy-heilman/search?date=3302008","type":"Text","label":{"none":["3/30/2008"]}}]}