{"@context":"https://iiif.io/api/presentation/3/context.json","id":"https://mathewjordan.github.io/canopy-heilman/api/facet/date/632009.json","type":"Collection","label":{"none":["6/3/2009"]},"items":[{"id":"https://digital.lib.utk.edu/assemble/manifest/heilman/613","type":"Manifest","label":{"en":["Hydrangea macrophylla, 0464"]},"thumbnail":[{"id":"https://digital.lib.utk.edu/iiif/2/collections~islandora~object~heilman%3A613~datastream~JP2/full/689,465/0/default.jpg","width":689,"height":465,"type":"Image","format":"image/jpeg","service":[{"@id":"https://digital.lib.utk.edu/iiif/2/collections~islandora~object~heilman%3A613~datastream~JP2","@type":"http://iiif.io/api/image/2/context.json","profile":"http://iiif.io/api/image/2/level2.json"}]}],"homepage":[{"id":"https://mathewjordan.github.io/canopy-heilman/works/hydrangea-macrophylla-0464","type":"Text","label":{"en":["Hydrangea macrophylla, 0464"]}}]},{"id":"https://digital.lib.utk.edu/assemble/manifest/heilman/615","type":"Manifest","label":{"en":["Hydrangea macrophylla, 0466"]},"thumbnail":[{"id":"https://digital.lib.utk.edu/iiif/2/collections~islandora~object~heilman%3A615~datastream~JP2/full/677,463/0/default.jpg","width":677,"height":463,"type":"Image","format":"image/jpeg","service":[{"@id":"https://digital.lib.utk.edu/iiif/2/collections~islandora~object~heilman%3A615~datastream~JP2","@type":"http://iiif.io/api/image/2/context.json","profile":"http://iiif.io/api/image/2/level2.json"}]}],"homepage":[{"id":"https://mathewjordan.github.io/canopy-heilman/works/hydrangea-macrophylla-0466","type":"Text","label":{"en":["Hydrangea macrophylla, 0466"]}}]}],"partOf":[{"id":"https://mathewjordan.github.io/canopy-heilman/api/facet/date.json","type":"Collection"}],"summary":{"none":["Date"]},"homepage":[{"id":"https://mathewjordan.github.io/canopy-heilman/search?date=632009","type":"Text","label":{"none":["6/3/2009"]}}]}