{"@context":"https://iiif.io/api/presentation/3/context.json","id":"https://mathewjordan.github.io/canopy-heilman/api/facet/date/8282007.json","type":"Collection","label":{"none":["8/28/2007"]},"items":[{"id":"https://digital.lib.utk.edu/assemble/manifest/heilman/1051","type":"Manifest","label":{"en":["Rosa, species indeterminate, 0907"]},"thumbnail":[{"id":"https://digital.lib.utk.edu/iiif/2/collections~islandora~object~heilman%3A1051~datastream~JP2/full/685,474/0/default.jpg","width":685,"height":474,"type":"Image","format":"image/jpeg","service":[{"@id":"https://digital.lib.utk.edu/iiif/2/collections~islandora~object~heilman%3A1051~datastream~JP2","@type":"http://iiif.io/api/image/2/context.json","profile":"http://iiif.io/api/image/2/level2.json"}]}],"homepage":[{"id":"https://mathewjordan.github.io/canopy-heilman/works/rosa-species-indeterminate-0907","type":"Text","label":{"en":["Rosa, species indeterminate, 0907"]}}]},{"id":"https://digital.lib.utk.edu/assemble/manifest/heilman/1050","type":"Manifest","label":{"en":["Rosa, species indeterminate, 0906"]},"thumbnail":[{"id":"https://digital.lib.utk.edu/iiif/2/collections~islandora~object~heilman%3A1050~datastream~JP2/full/686,470/0/default.jpg","width":686,"height":470,"type":"Image","format":"image/jpeg","service":[{"@id":"https://digital.lib.utk.edu/iiif/2/collections~islandora~object~heilman%3A1050~datastream~JP2","@type":"http://iiif.io/api/image/2/context.json","profile":"http://iiif.io/api/image/2/level2.json"}]}],"homepage":[{"id":"https://mathewjordan.github.io/canopy-heilman/works/rosa-species-indeterminate-0906","type":"Text","label":{"en":["Rosa, species indeterminate, 0906"]}}]}],"partOf":[{"id":"https://mathewjordan.github.io/canopy-heilman/api/facet/date.json","type":"Collection"}],"summary":{"none":["Date"]},"homepage":[{"id":"https://mathewjordan.github.io/canopy-heilman/search?date=8282007","type":"Text","label":{"none":["8/28/2007"]}}]}